tach/__init__.py
tach/__main__.py
tach/cache/__init__.py
tach/cache/access.py
tach/cache/setup.py
tach/check_external.py
tach/cli.py
tach/console.py
tach/constants/__init__.py
tach/errors/__init__.py
tach/extension.abi3.so
tach/extension.pyi
tach/filesystem/__init__.py
tach/filesystem/git_ops.py
tach/filesystem/install.py
tach/filesystem/project.py
tach/filesystem/service.py
tach/filesystem/tach.domain.toml
tach/hooks/__init__.py
tach/hooks/pre_commit.py
tach/icons.py
tach/init.py
tach/interactive/__init__.py
tach/interactive/modules.py
tach/logging/__init__.py
tach/logging/logger.py
tach/mod.py
tach/modularity.py
tach/parsing/__init__.py
tach/parsing/config.py
tach/pytest_plugin.py
tach/report.py
tach/show.py
tach/start.py
tach/test.py
tach/utils/__init__.py
tach/utils/display.py
tach/utils/exclude.py
tach/utils/external.py
tach-0.33.2.dist-info/METADATA
tach-0.33.2.dist-info/WHEEL
tach-0.33.2.dist-info/entry_points.txt
tach-0.33.2.dist-info/licenses/LICENSE
tach.libs/libgcc_s-262c4f60.so.1
tach-0.33.2.dist-info/RECORD
